[
null,
{"id":1,"atypeId":1,"description":"","etypeId":4,"traits":[{"code":22,"dataId":1,"value":0}],"iconIndex":135,"name":"-----Armors","note":"","params":[0,0,0,1,0,0,0,0],"price":100},
{"id":2,"atypeId":1,"description":"Armor made of tough cloth.","etypeId":4,"traits":[],"iconIndex":135,"name":"Cloth Armor","note":"","params":[0,0,0,2,0,0,0,0],"price":32},
{"id":3,"atypeId":1,"description":"Armor made of layered hide.\n+5% evasion chance","etypeId":4,"traits":[{"code":22,"dataId":1,"value":0.05}],"iconIndex":135,"name":"Leather Armor","note":"","params":[0,0,0,3,0,0,0,0],"price":68},
{"id":4,"atypeId":1,"description":"Armor made of iron.","etypeId":4,"traits":[{"code":22,"dataId":1,"value":0}],"iconIndex":135,"name":"Iron Armor","note":"","params":[0,0,0,13,0,0,0,0],"price":200},
{"id":5,"atypeId":1,"description":"Armor made of steel.","etypeId":4,"traits":[{"code":22,"dataId":1,"value":0}],"iconIndex":135,"name":"Steel Armor","note":"","params":[0,0,0,22,0,0,0,0],"price":380},
{"id":6,"atypeId":1,"description":"Armor made of carbon-steel.","etypeId":4,"traits":[{"code":22,"dataId":1,"value":0}],"iconIndex":135,"name":"Carbon-Steel Armor","note":"","params":[0,0,0,34,0,0,0,0],"price":950},
{"id":7,"atypeId":1,"description":"A breastplate made of dragon scales.","etypeId":4,"traits":[{"code":22,"dataId":1,"value":0}],"iconIndex":135,"name":"Dragonscale Breastplate","note":"","params":[0,0,0,35,0,0,0,0],"price":2880},
{"id":8,"atypeId":0,"description":"","etypeId":2,"traits":[{"code":22,"dataId":1,"value":0}],"iconIndex":0,"name":"","note":"","params":[0,0,0,0,0,0,0,0],"price":0},
{"id":9,"atypeId":1,"description":"","etypeId":4,"traits":[{"code":22,"dataId":1,"value":0}],"iconIndex":135,"name":"-----Helmets","note":"","params":[0,0,0,1,0,0,0,0],"price":100},
{"id":10,"atypeId":1,"description":"Headwear made of tough cloth.","etypeId":3,"traits":[],"iconIndex":130,"name":"Cloth cap","note":"","params":[5,0,1,0,0,0,0,0],"price":28},
{"id":11,"atypeId":1,"description":"Headwear made of layered hide.","etypeId":3,"traits":[],"iconIndex":130,"name":"Leather cap","note":"","params":[0,0,0,1,0,0,2,0],"price":60},
{"id":12,"atypeId":1,"description":"Headwear made of iron.","etypeId":3,"traits":[{"code":22,"dataId":1,"value":0}],"iconIndex":130,"name":"Iron helmet","note":"","params":[0,0,0,4,0,0,0,0],"price":150},
{"id":13,"atypeId":1,"description":"Headwear made of steel.","etypeId":3,"traits":[{"code":22,"dataId":1,"value":0}],"iconIndex":130,"name":"Steel helmet","note":"","params":[0,0,0,7,0,0,0,0],"price":320},
{"id":14,"atypeId":1,"description":"Headwear made of carbon-steel.","etypeId":3,"traits":[{"code":22,"dataId":1,"value":0}],"iconIndex":130,"name":"Carbon-Steel helmet","note":"","params":[0,0,0,11,0,0,0,0],"price":780},
{"id":15,"atypeId":1,"description":"Headwear made of dragon scales.","etypeId":3,"traits":[{"code":22,"dataId":1,"value":0}],"iconIndex":130,"name":"Dragonscale hood","note":"","params":[0,0,0,16,0,0,0,0],"price":2400},
{"id":16,"atypeId":0,"description":"","etypeId":2,"traits":[{"code":22,"dataId":1,"value":0}],"iconIndex":0,"name":"","note":"","params":[0,0,0,0,0,0,0,0],"price":0},
{"id":17,"atypeId":1,"description":"","etypeId":4,"traits":[{"code":22,"dataId":1,"value":0}],"iconIndex":135,"name":"-----Accessories","note":"","params":[0,0,0,1,0,0,0,0],"price":100},
{"id":18,"atypeId":1,"description":"A rock that increases Defense.","etypeId":2,"traits":[],"iconIndex":147,"name":"Guard Stone","note":"","params":[0,0,0,3,0,0,0,0],"price":70},
{"id":19,"atypeId":1,"description":"A ring that increases Defense.","etypeId":2,"traits":[{"code":22,"dataId":1,"value":0}],"iconIndex":145,"name":"Guard Ring","note":"","params":[0,0,0,8,0,0,0,0],"price":400},
{"id":20,"atypeId":1,"description":"A rock that increases Attack.","etypeId":2,"traits":[{"code":22,"dataId":1,"value":0}],"iconIndex":147,"name":"Power Stone","note":"","params":[0,0,5,0,0,0,0,0],"price":55},
{"id":21,"atypeId":1,"description":"A ring that increases Attack.","etypeId":0,"traits":[{"code":22,"dataId":1,"value":0}],"iconIndex":145,"name":"Power Ring","note":"","params":[0,0,15,0,0,0,0,0],"price":280},
{"id":22,"atypeId":1,"description":"A rock that increases Agility.","etypeId":0,"traits":[{"code":22,"dataId":1,"value":0}],"iconIndex":147,"name":"Speed Stone","note":"","params":[0,0,0,0,0,0,8,0],"price":65},
{"id":23,"atypeId":1,"description":"A ring that increases Agility.","etypeId":0,"traits":[{"code":22,"dataId":1,"value":0}],"iconIndex":145,"name":"Speed Ring","note":"","params":[0,0,0,0,0,0,26,0],"price":410},
{"id":24,"atypeId":1,"description":"A rock that reduces MP Cost by 20%.","etypeId":0,"traits":[{"code":23,"dataId":4,"value":0.8}],"iconIndex":147,"name":"MP Reserve Stone","note":"","params":[0,0,0,0,0,0,0,0],"price":220},
{"id":25,"atypeId":1,"description":"Decreases MP Cost Rate by half.","etypeId":0,"traits":[{"code":23,"dataId":4,"value":0.5}],"iconIndex":144,"name":"MP Keeper","note":"","params":[0,0,0,0,0,0,0,0],"price":980},
{"id":26,"atypeId":1,"description":"Allows you to carryover TP over into the\nnext battle.","etypeId":0,"traits":[{"code":62,"dataId":3,"value":1}],"iconIndex":144,"name":"TP Stocker","note":"","params":[0,0,0,0,0,0,0,0],"price":280},
{"id":27,"atypeId":1,"description":"Increases TP Charge Rate.","etypeId":0,"traits":[{"code":23,"dataId":5,"value":2}],"iconIndex":145,"name":"TP Charge Ring","note":"","params":[0,0,0,0,0,0,0,0],"price":400},
{"id":28,"atypeId":1,"description":"Damage inflicted by Fire, Water, Wind,\nand Earth attacks is halved.","etypeId":2,"traits":[{"code":11,"dataId":2,"value":0.5},{"code":11,"dataId":5,"value":0.5},{"code":11,"dataId":6,"value":0.5},{"code":11,"dataId":7,"value":0.5}],"iconIndex":145,"name":"Elemental Guard","note":"","params":[0,0,0,0,0,0,0,0],"price":700},
{"id":29,"atypeId":1,"description":"Increases crit rate, +15%","etypeId":2,"traits":[{"code":22,"dataId":2,"value":0.15}],"iconIndex":151,"name":"Spectacles","note":"","params":[0,0,0,0,0,0,0,0],"price":330},
{"id":30,"atypeId":0,"description":"","etypeId":2,"traits":[{"code":22,"dataId":1,"value":0}],"iconIndex":0,"name":"","note":"","params":[0,0,0,0,0,0,0,0],"price":0},
{"id":31,"atypeId":1,"description":"Used to test battles","etypeId":2,"traits":[],"iconIndex":40,"name":"TestHP","note":"","params":[20,0,0,0,0,0,0,0],"price":0},
{"id":32,"atypeId":0,"description":"","etypeId":2,"traits":[{"code":23,"dataId":9,"value":3},{"code":64,"dataId":4,"value":1}],"iconIndex":145,"name":"TestExp/Gold","note":"","params":[0,0,0,0,0,0,0,0],"price":0}
]